thales/__init__.py
thales/core.py
thales/complex/__init__.py
thales/complex/complexCore.py
thales/extras/__init__.py
thales/extras/conics.py
thales/extras/slopeField.py
thales-0.2.3.dist-info/LICENSE
thales-0.2.3.dist-info/METADATA
thales-0.2.3.dist-info/WHEEL
thales-0.2.3.dist-info/top_level.txt
thales-0.2.3.dist-info/RECORD
