Metadata-Version: 2.1
Name: thales
Version: 0.2.3
Summary: Thales Graphing Library
Home-page: UNKNOWN
Author: Jacob Singer
Author-email: <jesingermz@gmail.com>
License: UNKNOWN
Keywords: python,graphing,pygame
Platform: UNKNOWN
Classifier: Development Status :: 3 - Alpha
Classifier: Intended Audience :: Education
Classifier: Programming Language :: Python :: 2
Classifier: Programming Language :: Python :: 3
Classifier: Operating System :: MacOS :: MacOS X
Classifier: Operating System :: Microsoft :: Windows
License-File: LICENSE
Requires-Dist: pygame
Requires-Dist: sympy
